farcy/__init__.py
farcy/const.py
farcy/exceptions.py
farcy/handlers.py
farcy/helpers.py
farcy/objects.py
farcy-1.3.0.dist-info/METADATA
farcy-1.3.0.dist-info/RECORD
farcy-1.3.0.dist-info/WHEEL
farcy-1.3.0.dist-info/entry_points.txt
farcy-1.3.0.dist-info/top_level.txt
