Metadata-Version: 2.1
Name: farcy
Version: 1.3.0
Summary: A code review bot for github pull requests
Home-page: https://github.com/appfolio/farcy
Author: Bryce Boe
Author-email: bbzbryce@gmail.com
License: Simplified BSD License
Keywords: code review,pull request
Platform: UNKNOWN
Classifier: Intended Audience :: Developers
Classifier: License :: OSI Approved :: BSD License
Classifier: Operating System :: OS Independent
Classifier: Programming Language :: Python
Classifier: Programming Language :: Python :: 2.7
Classifier: Programming Language :: Python :: 3.4
Classifier: Programming Language :: Python :: 3.5
Provides-Extra: python
Requires-Dist: botocore (>=0.74.0)
Requires-Dist: docopt (>=0.6.2)
Requires-Dist: github3.py (>=1.0.1)
Requires-Dist: python-dateutil (<2.7.0)
Requires-Dist: update-checker (>=0.11)
Provides-Extra: python
Requires-Dist: flake8 (>=2.2.5); extra == 'python'
Requires-Dist: pep257 (>=0.3.2); extra == 'python'
